Workbook

Sheet Calculator
A2: DealWiseRent.com | Rental Property Investment Calculator
A4: 📝 INSTRUCTIONS: Enter values in BLUE cells. GREEN cells auto-calculate. Do NOT edit green cells.
B6: 💰 COST ASSUMPTIONS | E6: 🏦 FINANCING | H6: 📈 REVENUE & GROWTH | K6: 🏘 UNIT DETAILS
B7: Purchase Price | C7: 75000 | E7: Downpayment % | F7: 0.25 | H7: Monthly Rent / Unit | I7: 1300 | K7: Number of Units | L7: 1
B8: Improvements / Rehab | C8: 10000 | E8: Interest Rate (Annual) | F8: 0.0568 | H8: Vacancy Rate | I8: 0.05 | K8: Square Footage | L8: 1800
B9: Closing Costs | C9: 8000 | E9: Loan Term (Years) | F9: 30 | H9: Annual Revenue Growth | I9: 0.02 | K9: Avg Tenant Stay | L9: 2
B10: Land Value (25%) | C10: =C7*0.25 -> 18750 | E10: Finance Amount | F10: =C7*(1-F7) -> 56250 | H10: Annual Expense Growth | I10: 0.02 | K10: PM Fee (% of Income) | L10: 0.08
B11: Building Value (75%) | C11: =C7*0.75 -> 56250 | E11: Downpayment Amount | F11: =C7*F7 -> 18750 | H11: Property Taxes (Annual) | I11: 2500 | K11: Insurance (Annual) | L11: 700
B12: Total Investment Cost | C12: =C7+C8+C9 -> 93000 | E12: Monthly Mortgage Pmt | F12: =IFERROR(ABS(PMT(F8/12,F9*12,F10)),0) -> 325.76267 | H12: Maintenance (Annual) | I12: 500 | K12: HOA Dues (Monthly) | L12: 0
E13: Total Cash Outlay | F13: =F11+C8+C9 -> 36750 | H13: Tenant Placement (Yr1) | I13: 650 | K13: Other Annual Expenses | L13: 0
B15: 🔵 Blue = User Input | E15: 🟢 Green = Auto-Calculated | H15: ⚠ Yellow = Needs Attention | K15: 📊 See Charts tab for visuals
B17: 📊 YEAR 1 RESULTS SUMMARY — Outsourced PM vs. Self-Managed
B18: METRIC | E18: OUTSOURCED PROP. MGMT | H18: SELF-MANAGED | K18: NOTES
B19: Gross Annual Rent | E19: =I7*12*L7 -> 15600 | H19: =I7*12*L7 -> 15600 | K19: Rent × 12 months × units
B20: Vacancy / Credit Loss (−) | E20: =-I7*12*L7*I8 -> -780 | H20: =-I7*12*L7*I8 -> -780 | K20: Vacancy rate × gross rent
B21: Effective Gross Income (EGI) | E21: =E19+E20 -> 14820 | H21: =H19+H20 -> 14820 | K21: Revenue after vacancy
B22: ─── Operating Expenses ───
B23: Property Taxes | E23: =-I11 -> -2500 | H23: =-I11 -> -2500 | K23: Annual
B24: Insurance | E24: =-L11 -> -700 | H24: =-L11 -> -700 | K24: Annual
B25: Maintenance & Repairs | E25: =-I12 -> -500 | H25: =-I12 -> -500 | K25: Annual
B26: PM Fee (outsourced / self) | E26: =-E21*L10 -> -1185.6 | H26: =0 -> 0 | K26: % of EGI outsourced; $0 self-managed
B27: HOA Dues | E27: =IF(L12>0,-L12*12,0) -> 0 | H27: =IF(L12>0,-L12*12,0) -> 0 | K27: Monthly×12
B28: Tenant Placement Fee (Yr1) | E28: =-I13 -> -650 | H28: =-I13 -> -650 | K28: First year only
B29: Other Annual Expenses | E29: =-L13 -> 0 | H29: =-L13 -> 0 | K29: Annual
B30: Total Operating Expenses | E30: =E23+E24+E25+E26+E27+E28+E29 -> -5535.6 | H30: =H23+H24+H25+H26+H27+H28+H29 -> -4350 | K30: Sum of all operating costs
B31: ─── Net Income & Cash Flow ───
B32: Net Operating Income (NOI) | E32: =E21+E30 -> 9284.4 | H32: =H21+H30 -> 10470 | K32: EGI + Total Expenses (expenses are negative)
B33: Annual Mortgage Payments | E33: =-F12*12 -> -3909.152 | H33: =-F12*12 -> -3909.152 | K33: Monthly payment × 12
B34: Annual Cash Flow | E34: =E32+E33 -> 5375.248 | H34: =H32+H33 -> 6560.848 | K34: NOI – Debt Service
B35: Monthly Cash Flow | E35: =E34/12 -> 447.93733 | H35: =H34/12 -> 546.73733 | K35: Annual CF ÷ 12
B36: ─── Returns & Ratios ───
B37: Cash ROI | E37: =IFERROR(E34/F13,0) -> 0.14626525 | H37: =IFERROR(H34/F13,0) -> 0.17852648 | K37: Annual CF ÷ Cash Outlay
B38: Total ROI (CF + Equity, Yr1) | E38: =IFERROR((E34-CUMPRINC(F8/12,F9*12,F10,1,12,0))/F13,0) -> 0.16621192 | H38: =IFERROR((H34-CUMPRINC(F8/12,F9*12,F10,1,12,0))/F13,0) -> 0.19847315 | K38: Includes principal paydown
B39: Cap Rate (NOI / Total Cost) | E39: =IFERROR(E32/C12,0) -> 0.099832258 | H39: =IFERROR(H32/C12,0) -> 0.11258065 | K39: Unlevered yield on cost
B40: Gross Rent Multiplier (GRM) | E40: =IFERROR(C7/E19,0) -> 4.8076923 | H40: =IFERROR(C7/H19,0) -> 4.8076923 | K40: Purchase Price ÷ Gross Rent
B41: Rent per Sq Ft / Year | E41: =IFERROR(I7*12/L8,0) -> 8.6666667 | H41: =IFERROR(I7*12/L8,0) -> 8.6666667 | K41: Monthly rent × 12 ÷ sq ft
B43: 📊 30-YEAR CASH FLOW & RETURNS PROJECTION (Outsourced Property Management)
B44: Year | C44: Gross Rent | D44: Eff. Gross Income | E44: Total Expenses | F44: NOI | G44: Annual Mortgage | H44: Annual Cash Flow | I44: Cash ROI % | J44: Equity Gained | K44: Cum. Equity | L44: Total ROI %
B45: 1 | C45: =$I$7*12*$L$7 -> 15600 | D45: =C45*(1-$I$8) -> 14820 | E45: =($I$11+$L$11+$I$12+IF($L$12>0,$L$12*12,0)+$I$13+$L$13)+D45*$L$10 -> 5535.6 | F45: =D45-E45 -> 9284.4 | G45: =$F$12*12 -> 3909.152 | H45: =F45-G45 -> 5375.248 | I45: =IFERROR(H45/$F$13,0) -> 0.14626525 | J45: =IFERROR(-CUMPRINC($F$8/12,$F$9*12,$F$10,(1-1)*12+1,1*12,0),0) -> 733.04028 | K45: =J45 -> 733.04028 | L45: =IFERROR((H45+J45)/$F$13,0) -> 0.16621192
B46: 2 | C46: =C45*(1+$I$9) -> 15912 | D46: =C46*(1-$I$8) -> 15116.4 | E46: =($I$11*(1+$I$10)^(2-1)+$L$11*(1+$I$10)^(2-1)+$I$12*(1+$I$10)^(2-1)+IF($L$12>0,$L$12*12*(1+$I$10)^(2-1),0)+$L$13*(1+$I$10)^(2-1))+D46*$L$10 -> 4983.312 | F46: =D46-E46 -> 10133.088 | G46: =$F$12*12 -> 3909.152 | H46: =F46-G46 -> 6223.936 | I46: =IFERROR(H46/$F$13,0) -> 0.1693588 | J46: =IFERROR(-CUMPRINC($F$8/12,$F$9*12,$F$10,(2-1)*12+1,2*12,0),0) -> 775.7782 | K46: =K45+J46 -> 1508.8185 | L46: =IFERROR((H46+J46)/$F$13,0) -> 0.19046841
B47: 3 | C47: =C46*(1+$I$9) -> 16230.24 | D47: =C47*(1-$I$8) -> 15418.728 | E47: =($I$11*(1+$I$10)^(3-1)+$L$11*(1+$I$10)^(3-1)+$I$12*(1+$I$10)^(3-1)+IF($L$12>0,$L$12*12*(1+$I$10)^(3-1),0)+$L$13*(1+$I$10)^(3-1))+D47*$L$10 -> 5082.9782 | F47: =D47-E47 -> 10335.75 | G47: =$F$12*12 -> 3909.152 | H47: =F47-G47 -> 6426.5977 | I47: =IFERROR(H47/$F$13,0) -> 0.17487341 | J47: =IFERROR(-CUMPRINC($F$8/12,$F$9*12,$F$10,(3-1)*12+1,3*12,0),0) -> 821.00783 | K47: =K46+J47 -> 2329.8263 | L47: =IFERROR((H47+J47)/$F$13,0) -> 0.19721376
B48: 4 | C48: =C47*(1+$I$9) -> 16554.845 | D48: =C48*(1-$I$8) -> 15727.103 | E48: =($I$11*(1+$I$10)^(4-1)+$L$11*(1+$I$10)^(4-1)+$I$12*(1+$I$10)^(4-1)+IF($L$12>0,$L$12*12*(1+$I$10)^(4-1),0)+$L$13*(1+$I$10)^(4-1))+D48*$L$10 -> 5184.6378 | F48: =D48-E48 -> 10542.465 | G48: =$F$12*12 -> 3909.152 | H48: =F48-G48 -> 6633.3127 | I48: =IFERROR(H48/$F$13,0) -> 0.18049831 | J48: =IFERROR(-CUMPRINC($F$8/12,$F$9*12,$F$10,(4-1)*12+1,4*12,0),0) -> 868.87445 | K48: =K47+J48 -> 3198.7008 | L48: =IFERROR((H48+J48)/$F$13,0) -> 0.20414115
B49: 5 | C49: =C48*(1+$I$9) -> 16885.942 | D49: =C49*(1-$I$8) -> 16041.645 | E49: =($I$11*(1+$I$10)^(5-1)+$L$11*(1+$I$10)^(5-1)+$I$12*(1+$I$10)^(5-1)+IF($L$12>0,$L$12*12*(1+$I$10)^(5-1),0)+$L$13*(1+$I$10)^(5-1))+D49*$L$10 -> 5288.3306 | F49: =D49-E49 -> 10753.314 | G49: =$F$12*12 -> 3909.152 | H49: =F49-G49 -> 6844.162 | I49: =IFERROR(H49/$F$13,0) -> 0.1862357 | J49: =IFERROR(-CUMPRINC($F$8/12,$F$9*12,$F$10,(5-1)*12+1,5*12,0),0) -> 919.53181 | K49: =K48+J49 -> 4118.2326 | L49: =IFERROR((H49+J49)/$F$13,0) -> 0.21125697
B50: 6 | C50: =C49*(1+$I$9) -> 17223.661 | D50: =C50*(1-$I$8) -> 16362.478 | E50: =($I$11*(1+$I$10)^(6-1)+$L$11*(1+$I$10)^(6-1)+$I$12*(1+$I$10)^(6-1)+IF($L$12>0,$L$12*12*(1+$I$10)^(6-1),0)+$L$13*(1+$I$10)^(6-1))+D50*$L$10 -> 5394.0972 | F50: =D50-E50 -> 10968.38 | G50: =$F$12*12 -> 3909.152 | H50: =F50-G50 -> 7059.2283 | I50: =IFERROR(H50/$F$13,0) -> 0.19208784 | J50: =IFERROR(-CUMPRINC($F$8/12,$F$9*12,$F$10,(6-1)*12+1,6*12,0),0) -> 973.14261 | K50: =K49+J50 -> 5091.3752 | L50: =IFERROR((H50+J50)/$F$13,0) -> 0.21856792
B51: 7 | C51: =C50*(1+$I$9) -> 17568.134 | D51: =C51*(1-$I$8) -> 16689.727 | E51: =($I$11*(1+$I$10)^(7-1)+$L$11*(1+$I$10)^(7-1)+$I$12*(1+$I$10)^(7-1)+IF($L$12>0,$L$12*12*(1+$I$10)^(7-1),0)+$L$13*(1+$I$10)^(7-1))+D51*$L$10 -> 5501.9791 | F51: =D51-E51 -> 11187.748 | G51: =$F$12*12 -> 3909.152 | H51: =F51-G51 -> 7278.5959 | I51: =IFERROR(H51/$F$13,0) -> 0.19805703 | J51: =IFERROR(-CUMPRINC($F$8/12,$F$9*12,$F$10,(7-1)*12+1,7*12,0),0) -> 1029.879 | K51: =K50+J51 -> 6121.2542 | L51: =IFERROR((H51+J51)/$F$13,0) -> 0.22608095
B52: 8 | C52: =C51*(1+$I$9) -> 17919.496 | D52: =C52*(1-$I$8) -> 17023.522 | E52: =($I$11*(1+$I$10)^(8-1)+$L$11*(1+$I$10)^(8-1)+$I$12*(1+$I$10)^(8-1)+IF($L$12>0,$L$12*12*(1+$I$10)^(8-1),0)+$L$13*(1+$I$10)^(8-1))+D52*$L$10 -> 5612.0187 | F52: =D52-E52 -> 11411.503 | G52: =$F$12*12 -> 3909.152 | H52: =F52-G52 -> 7502.3509 | I52: =IFERROR(H52/$F$13,0) -> 0.2041456 | J52: =IFERROR(-CUMPRINC($F$8/12,$F$9*12,$F$10,(8-1)*12+1,8*12,0),0) -> 1089.9233 | K52: =K51+J52 -> 7211.1775 | L52: =IFERROR((H52+J52)/$F$13,0) -> 0.23380338
B53: 9 | C53: =C52*(1+$I$9) -> 18277.886 | D53: =C53*(1-$I$8) -> 17363.992 | E53: =($I$11*(1+$I$10)^(9-1)+$L$11*(1+$I$10)^(9-1)+$I$12*(1+$I$10)^(9-1)+IF($L$12>0,$L$12*12*(1+$I$10)^(9-1),0)+$L$13*(1+$I$10)^(9-1))+D53*$L$10 -> 5724.2591 | F53: =D53-E53 -> 11639.733 | G53: =$F$12*12 -> 3909.152 | H53: =F53-G53 -> 7730.5809 | I53: =IFERROR(H53/$F$13,0) -> 0.21035594 | J53: =IFERROR(-CUMPRINC($F$8/12,$F$9*12,$F$10,(9-1)*12+1,9*12,0),0) -> 1153.4683 | K53: =K52+J53 -> 8364.6459 | L53: =IFERROR((H53+J53)/$F$13,0) -> 0.24174284
B54: 10 | C54: =C53*(1+$I$9) -> 18643.444 | D54: =C54*(1-$I$8) -> 17711.272 | E54: =($I$11*(1+$I$10)^(10-1)+$L$11*(1+$I$10)^(10-1)+$I$12*(1+$I$10)^(10-1)+IF($L$12>0,$L$12*12*(1+$I$10)^(10-1),0)+$L$13*(1+$I$10)^(10-1))+D54*$L$10 -> 5838.7443 | F54: =D54-E54 -> 11872.528 | G54: =$F$12*12 -> 3909.152 | H54: =F54-G54 -> 7963.3756 | I54: =IFERROR(H54/$F$13,0) -> 0.21669049 | J54: =IFERROR(-CUMPRINC($F$8/12,$F$9*12,$F$10,(10-1)*12+1,10*12,0),0) -> 1220.7182 | K54: =K53+J54 -> 9585.364 | L54: =IFERROR((H54+J54)/$F$13,0) -> 0.24990731
B55: 11 | C55: =C54*(1+$I$9) -> 19016.313 | D55: =C55*(1-$I$8) -> 18065.497 | E55: =($I$11*(1+$I$10)^(11-1)+$L$11*(1+$I$10)^(11-1)+$I$12*(1+$I$10)^(11-1)+IF($L$12>0,$L$12*12*(1+$I$10)^(11-1),0)+$L$13*(1+$I$10)^(11-1))+D55*$L$10 -> 5955.5191 | F55: =D55-E55 -> 12109.978 | G55: =$F$12*12 -> 3909.152 | H55: =F55-G55 -> 8200.8261 | I55: =IFERROR(H55/$F$13,0) -> 0.22315173 | J55: =IFERROR(-CUMPRINC($F$8/12,$F$9*12,$F$10,(11-1)*12+1,11*12,0),0) -> 1291.8888 | K55: =K54+J55 -> 10877.253 | L55: =IFERROR((H55+J55)/$F$13,0) -> 0.25830517
B56: 12 | C56: =C55*(1+$I$9) -> 19396.639 | D56: =C56*(1-$I$8) -> 18426.807 | E56: =($I$11*(1+$I$10)^(12-1)+$L$11*(1+$I$10)^(12-1)+$I$12*(1+$I$10)^(12-1)+IF($L$12>0,$L$12*12*(1+$I$10)^(12-1),0)+$L$13*(1+$I$10)^(12-1))+D56*$L$10 -> 6074.6295 | F56: =D56-E56 -> 12352.178 | G56: =$F$12*12 -> 3909.152 | H56: =F56-G56 -> 8443.0257 | I56: =IFERROR(H56/$F$13,0) -> 0.2297422 | J56: =IFERROR(-CUMPRINC($F$8/12,$F$9*12,$F$10,(12-1)*12+1,12*12,0),0) -> 1367.2089 | K56: =K55+J56 -> 12244.462 | L56: =IFERROR((H56+J56)/$F$13,0) -> 0.26694516
B57: 13 | C57: =C56*(1+$I$9) -> 19784.572 | D57: =C57*(1-$I$8) -> 18795.343 | E57: =($I$11*(1+$I$10)^(13-1)+$L$11*(1+$I$10)^(13-1)+$I$12*(1+$I$10)^(13-1)+IF($L$12>0,$L$12*12*(1+$I$10)^(13-1),0)+$L$13*(1+$I$10)^(13-1))+D57*$L$10 -> 6196.1221 | F57: =D57-E57 -> 12599.221 | G57: =$F$12*12 -> 3909.152 | H57: =F57-G57 -> 8690.0692 | I57: =IFERROR(H57/$F$13,0) -> 0.23646447 | J57: =IFERROR(-CUMPRINC($F$8/12,$F$9*12,$F$10,(13-1)*12+1,13*12,0),0) -> 1446.9202 | K57: =K56+J57 -> 13691.382 | L57: =IFERROR((H57+J57)/$F$13,0) -> 0.27583645
B58: 14 | C58: =C57*(1+$I$9) -> 20180.263 | D58: =C58*(1-$I$8) -> 19171.25 | E58: =($I$11*(1+$I$10)^(14-1)+$L$11*(1+$I$10)^(14-1)+$I$12*(1+$I$10)^(14-1)+IF($L$12>0,$L$12*12*(1+$I$10)^(14-1),0)+$L$13*(1+$I$10)^(14-1))+D58*$L$10 -> 6320.0446 | F58: =D58-E58 -> 12851.206 | G58: =$F$12*12 -> 3909.152 | H58: =F58-G58 -> 8942.0537 | I58: =IFERROR(H58/$F$13,0) -> 0.24332119 | J58: =IFERROR(-CUMPRINC($F$8/12,$F$9*12,$F$10,(14-1)*12+1,14*12,0),0) -> 1531.279 | K58: =K57+J58 -> 15222.661 | L58: =IFERROR((H58+J58)/$F$13,0) -> 0.28498864
B59: 15 | C59: =C58*(1+$I$9) -> 20583.869 | D59: =C59*(1-$I$8) -> 19554.675 | E59: =($I$11*(1+$I$10)^(15-1)+$L$11*(1+$I$10)^(15-1)+$I$12*(1+$I$10)^(15-1)+IF($L$12>0,$L$12*12*(1+$I$10)^(15-1),0)+$L$13*(1+$I$10)^(15-1))+D59*$L$10 -> 6446.4454 | F59: =D59-E59 -> 13108.23 | G59: =$F$12*12 -> 3909.152 | H59: =F59-G59 -> 9199.0778 | I59: =IFERROR(H59/$F$13,0) -> 0.25031504 | J59: =IFERROR(-CUMPRINC($F$8/12,$F$9*12,$F$10,(15-1)*12+1,15*12,0),0) -> 1620.556 | K59: =K58+J59 -> 16843.217 | L59: =IFERROR((H59+J59)/$F$13,0) -> 0.2944118
B60: 16 | C60: =C59*(1+$I$9) -> 20995.546 | D60: =C60*(1-$I$8) -> 19945.769 | E60: =($I$11*(1+$I$10)^(16-1)+$L$11*(1+$I$10)^(16-1)+$I$12*(1+$I$10)^(16-1)+IF($L$12>0,$L$12*12*(1+$I$10)^(16-1),0)+$L$13*(1+$I$10)^(16-1))+D60*$L$10 -> 6575.3744 | F60: =D60-E60 -> 13370.394 | G60: =$F$12*12 -> 3909.152 | H60: =F60-G60 -> 9461.2424 | I60: =IFERROR(H60/$F$13,0) -> 0.25744877 | J60: =IFERROR(-CUMPRINC($F$8/12,$F$9*12,$F$10,(16-1)*12+1,16*12,0),0) -> 1715.0381 | K60: =K59+J60 -> 18558.255 | L60: =IFERROR((H60+J60)/$F$13,0) -> 0.30411648
B61: 17 | C61: =C60*(1+$I$9) -> 21415.457 | D61: =C61*(1-$I$8) -> 20344.684 | E61: =($I$11*(1+$I$10)^(17-1)+$L$11*(1+$I$10)^(17-1)+$I$12*(1+$I$10)^(17-1)+IF($L$12>0,$L$12*12*(1+$I$10)^(17-1),0)+$L$13*(1+$I$10)^(17-1))+D61*$L$10 -> 6706.8818 | F61: =D61-E61 -> 13637.802 | G61: =$F$12*12 -> 3909.152 | H61: =F61-G61 -> 9728.6503 | I61: =IFERROR(H61/$F$13,0) -> 0.26472518 | J61: =IFERROR(-CUMPRINC($F$8/12,$F$9*12,$F$10,(17-1)*12+1,17*12,0),0) -> 1815.0288 | K61: =K60+J61 -> 20373.284 | L61: =IFERROR((H61+J61)/$F$13,0) -> 0.31411372
B62: 18 | C62: =C61*(1+$I$9) -> 21843.766 | D62: =C62*(1-$I$8) -> 20751.578 | E62: =($I$11*(1+$I$10)^(18-1)+$L$11*(1+$I$10)^(18-1)+$I$12*(1+$I$10)^(18-1)+IF($L$12>0,$L$12*12*(1+$I$10)^(18-1),0)+$L$13*(1+$I$10)^(18-1))+D62*$L$10 -> 6841.0195 | F62: =D62-E62 -> 13910.558 | G62: =$F$12*12 -> 3909.152 | H62: =F62-G62 -> 10001.406 | I62: =IFERROR(H62/$F$13,0) -> 0.27214711 | J62: =IFERROR(-CUMPRINC($F$8/12,$F$9*12,$F$10,(18-1)*12+1,18*12,0),0) -> 1920.8491 | K62: =K61+J62 -> 22294.133 | L62: =IFERROR((H62+J62)/$F$13,0) -> 0.32441511
B63: 19 | C63: =C62*(1+$I$9) -> 22280.641 | D63: =C63*(1-$I$8) -> 21166.609 | E63: =($I$11*(1+$I$10)^(19-1)+$L$11*(1+$I$10)^(19-1)+$I$12*(1+$I$10)^(19-1)+IF($L$12>0,$L$12*12*(1+$I$10)^(19-1),0)+$L$13*(1+$I$10)^(19-1))+D63*$L$10 -> 6977.8399 | F63: =D63-E63 -> 14188.77 | G63: =$F$12*12 -> 3909.152 | H63: =F63-G63 -> 10279.617 | I63: =IFERROR(H63/$F$13,0) -> 0.27971748 | J63: =IFERROR(-CUMPRINC($F$8/12,$F$9*12,$F$10,(19-1)*12+1,19*12,0),0) -> 2032.8389 | K63: =K62+J63 -> 24326.972 | L63: =IFERROR((H63+J63)/$F$13,0) -> 0.33503283
B64: 20 | C64: =C63*(1+$I$9) -> 22726.254 | D64: =C64*(1-$I$8) -> 21589.942 | E64: =($I$11*(1+$I$10)^(20-1)+$L$11*(1+$I$10)^(20-1)+$I$12*(1+$I$10)^(20-1)+IF($L$12>0,$L$12*12*(1+$I$10)^(20-1),0)+$L$13*(1+$I$10)^(20-1))+D64*$L$10 -> 7117.3967 | F64: =D64-E64 -> 14472.545 | G64: =$F$12*12 -> 3909.152 | H64: =F64-G64 -> 10563.393 | I64: =IFERROR(H64/$F$13,0) -> 0.28743926 | J64: =IFERROR(-CUMPRINC($F$8/12,$F$9*12,$F$10,(20-1)*12+1,20*12,0),0) -> 2151.3581 | K64: =K63+J64 -> 26478.33 | L64: =IFERROR((H64+J64)/$F$13,0) -> 0.34597962
B65: 21 | C65: =C64*(1+$I$9) -> 23180.779 | D65: =C65*(1-$I$8) -> 22021.74 | E65: =($I$11*(1+$I$10)^(21-1)+$L$11*(1+$I$10)^(21-1)+$I$12*(1+$I$10)^(21-1)+IF($L$12>0,$L$12*12*(1+$I$10)^(21-1),0)+$L$13*(1+$I$10)^(21-1))+D65*$L$10 -> 7259.7446 | F65: =D65-E65 -> 14761.996 | G65: =$F$12*12 -> 3909.152 | H65: =F65-G65 -> 10852.844 | I65: =IFERROR(H65/$F$13,0) -> 0.29531548 | J65: =IFERROR(-CUMPRINC($F$8/12,$F$9*12,$F$10,(21-1)*12+1,21*12,0),0) -> 2276.7871 | K65: =K64+J65 -> 28755.117 | L65: =IFERROR((H65+J65)/$F$13,0) -> 0.35726887
B66: 22 | C66: =C65*(1+$I$9) -> 23644.395 | D66: =C66*(1-$I$8) -> 22462.175 | E66: =($I$11*(1+$I$10)^(22-1)+$L$11*(1+$I$10)^(22-1)+$I$12*(1+$I$10)^(22-1)+IF($L$12>0,$L$12*12*(1+$I$10)^(22-1),0)+$L$13*(1+$I$10)^(22-1))+D66*$L$10 -> 7404.9395 | F66: =D66-E66 -> 15057.236 | G66: =$F$12*12 -> 3909.152 | H66: =F66-G66 -> 11148.084 | I66: =IFERROR(H66/$F$13,0) -> 0.30334922 | J66: =IFERROR(-CUMPRINC($F$8/12,$F$9*12,$F$10,(22-1)*12+1,22*12,0),0) -> 2409.529 | K66: =K65+J66 -> 31164.646 | L66: =IFERROR((H66+J66)/$F$13,0) -> 0.36891463
B67: 23 | C67: =C66*(1+$I$9) -> 24117.283 | D67: =C67*(1-$I$8) -> 22911.419 | E67: =($I$11*(1+$I$10)^(23-1)+$L$11*(1+$I$10)^(23-1)+$I$12*(1+$I$10)^(23-1)+IF($L$12>0,$L$12*12*(1+$I$10)^(23-1),0)+$L$13*(1+$I$10)^(23-1))+D67*$L$10 -> 7553.0383 | F67: =D67-E67 -> 15358.38 | G67: =$F$12*12 -> 3909.152 | H67: =F67-G67 -> 11449.228 | I67: =IFERROR(H67/$F$13,0) -> 0.31154363 | J67: =IFERROR(-CUMPRINC($F$8/12,$F$9*12,$F$10,(23-1)*12+1,23*12,0),0) -> 2550.01 | K67: =K66+J67 -> 33714.656 | L67: =IFERROR((H67+J67)/$F$13,0) -> 0.38093166
B68: 24 | C68: =C67*(1+$I$9) -> 24599.629 | D68: =C68*(1-$I$8) -> 23369.647 | E68: =($I$11*(1+$I$10)^(24-1)+$L$11*(1+$I$10)^(24-1)+$I$12*(1+$I$10)^(24-1)+IF($L$12>0,$L$12*12*(1+$I$10)^(24-1),0)+$L$13*(1+$I$10)^(24-1))+D68*$L$10 -> 7704.099 | F68: =D68-E68 -> 15665.548 | G68: =$F$12*12 -> 3909.152 | H68: =F68-G68 -> 11756.396 | I68: =IFERROR(H68/$F$13,0) -> 0.31990193 | J68: =IFERROR(-CUMPRINC($F$8/12,$F$9*12,$F$10,(24-1)*12+1,24*12,0),0) -> 2698.6814 | K68: =K67+J68 -> 36413.337 | L68: =IFERROR((H68+J68)/$F$13,0) -> 0.39333544
B69: 25 | C69: =C68*(1+$I$9) -> 25091.621 | D69: =C69*(1-$I$8) -> 23837.04 | E69: =($I$11*(1+$I$10)^(25-1)+$L$11*(1+$I$10)^(25-1)+$I$12*(1+$I$10)^(25-1)+IF($L$12>0,$L$12*12*(1+$I$10)^(25-1),0)+$L$13*(1+$I$10)^(25-1))+D69*$L$10 -> 7858.181 | F69: =D69-E69 -> 15978.859 | G69: =$F$12*12 -> 3909.152 | H69: =F69-G69 -> 12069.707 | I69: =IFERROR(H69/$F$13,0) -> 0.3284274 | J69: =IFERROR(-CUMPRINC($F$8/12,$F$9*12,$F$10,(25-1)*12+1,25*12,0),0) -> 2856.0207 | K69: =K68+J69 -> 39269.358 | L69: =IFERROR((H69+J69)/$F$13,0) -> 0.40614225
B70: 26 | C70: =C69*(1+$I$9) -> 25593.454 | D70: =C70*(1-$I$8) -> 24313.781 | E70: =($I$11*(1+$I$10)^(26-1)+$L$11*(1+$I$10)^(26-1)+$I$12*(1+$I$10)^(26-1)+IF($L$12>0,$L$12*12*(1+$I$10)^(26-1),0)+$L$13*(1+$I$10)^(26-1))+D70*$L$10 -> 8015.3446 | F70: =D70-E70 -> 16298.436 | G70: =$F$12*12 -> 3909.152 | H70: =F70-G70 -> 12389.284 | I70: =IFERROR(H70/$F$13,0) -> 0.33712338 | J70: =IFERROR(-CUMPRINC($F$8/12,$F$9*12,$F$10,(26-1)*12+1,26*12,0),0) -> 3022.5332 | K70: =K69+J70 -> 42291.891 | L70: =IFERROR((H70+J70)/$F$13,0) -> 0.41936918
B71: 27 | C71: =C70*(1+$I$9) -> 26105.323 | D71: =C71*(1-$I$8) -> 24800.056 | E71: =($I$11*(1+$I$10)^(27-1)+$L$11*(1+$I$10)^(27-1)+$I$12*(1+$I$10)^(27-1)+IF($L$12>0,$L$12*12*(1+$I$10)^(27-1),0)+$L$13*(1+$I$10)^(27-1))+D71*$L$10 -> 8175.6515 | F71: =D71-E71 -> 16624.405 | G71: =$F$12*12 -> 3909.152 | H71: =F71-G71 -> 12715.253 | I71: =IFERROR(H71/$F$13,0) -> 0.34599328 | J71: =IFERROR(-CUMPRINC($F$8/12,$F$9*12,$F$10,(27-1)*12+1,27*12,0),0) -> 3198.7537 | K71: =K70+J71 -> 45490.645 | L71: =IFERROR((H71+J71)/$F$13,0) -> 0.43303419
B72: 28 | C72: =C71*(1+$I$9) -> 26627.429 | D72: =C72*(1-$I$8) -> 25296.058 | E72: =($I$11*(1+$I$10)^(28-1)+$L$11*(1+$I$10)^(28-1)+$I$12*(1+$I$10)^(28-1)+IF($L$12>0,$L$12*12*(1+$I$10)^(28-1),0)+$L$13*(1+$I$10)^(28-1))+D72*$L$10 -> 8339.1646 | F72: =D72-E72 -> 16956.893 | G72: =$F$12*12 -> 3909.152 | H72: =F72-G72 -> 13047.741 | I72: =IFERROR(H72/$F$13,0) -> 0.35504057 | J72: =IFERROR(-CUMPRINC($F$8/12,$F$9*12,$F$10,(28-1)*12+1,28*12,0),0) -> 3385.2483 | K72: =K71+J72 -> 48875.893 | L72: =IFERROR((H72+J72)/$F$13,0) -> 0.44715617
B73: 29 | C73: =C72*(1+$I$9) -> 27159.978 | D73: =C73*(1-$I$8) -> 25801.979 | E73: =($I$11*(1+$I$10)^(29-1)+$L$11*(1+$I$10)^(29-1)+$I$12*(1+$I$10)^(29-1)+IF($L$12>0,$L$12*12*(1+$I$10)^(29-1),0)+$L$13*(1+$I$10)^(29-1))+D73*$L$10 -> 8505.9479 | F73: =D73-E73 -> 17296.031 | G73: =$F$12*12 -> 3909.152 | H73: =F73-G73 -> 13386.879 | I73: =IFERROR(H73/$F$13,0) -> 0.36426881 | J73: =IFERROR(-CUMPRINC($F$8/12,$F$9*12,$F$10,(29-1)*12+1,29*12,0),0) -> 3582.616 | K73: =K72+J73 -> 52458.509 | L73: =IFERROR((H73+J73)/$F$13,0) -> 0.46175496
B74: 30 | C74: =C73*(1+$I$9) -> 27703.177 | D74: =C74*(1-$I$8) -> 26318.018 | E74: =($I$11*(1+$I$10)^(30-1)+$L$11*(1+$I$10)^(30-1)+$I$12*(1+$I$10)^(30-1)+IF($L$12>0,$L$12*12*(1+$I$10)^(30-1),0)+$L$13*(1+$I$10)^(30-1))+D74*$L$10 -> 8676.0668 | F74: =D74-E74 -> 17641.951 | G74: =$F$12*12 -> 3909.152 | H74: =F74-G74 -> 13732.799 | I74: =IFERROR(H74/$F$13,0) -> 0.37368162 | J74: =IFERROR(-CUMPRINC($F$8/12,$F$9*12,$F$10,(30-1)*12+1,30*12,0),0) -> 3791.4907 | K74: =K73+J74 -> 56250 | L74: =IFERROR((H74+J74)/$F$13,0) -> 0.47685143
B75: 30-YEAR TOTALS | C75: =SUM(C45:C74) -> 632862.04 | D75: =SUM(D45:D74) -> 601218.93 | E75: =SUM(E45:E74) -> 198849.41 | F75: =SUM(F45:F74) -> 402369.53 | G75: =SUM(G45:G74) -> 117274.56 | H75: =SUM(H45:H74) -> 285094.96 | I75: =AVERAGE(I45:I74) -> 0.25858954 | J75: =SUM(J45:J74) -> 56250 | K75: =K74 -> 56250 | L75: =AVERAGE(L45:L74) -> 0.30960995
B77: ⚠ DISCLAIMER: All projections and calculations in this worksheet are estimates for informational purposes only and may contain errors or omissions. Assumptions about rent growth, expense growth, and occupancy may differ from actual market conditions. Past performance does not guarantee future results. Always consult a licensed real estate professional, CPA, or financial advisor before making any investment decisions. © 2025 DealWiseRent.com
B78: © 2025 DealWiseRent.com | Professional Rental Investment Analysis | www.DealWiseRent.com

Sheet Dashboard
A2: 🏠 DealWiseRent.com
A4: RENTAL PROPERTY INVESTMENT ANALYSIS TOOL
A6: ⚠ DISCLAIMER: This tool provides rental property investment estimates for informational purposes only. Calculations may contain errors or omissions. Always perform your own due diligence and consult a licensed real estate professional or financial advisor before making any investment decision. DealWiseRent.com assumes no liability for decisions based on this analysis.
A8: 📊 INVESTMENT SUMMARY — Update inputs on the ➜ Calculator sheet
B9: PURCHASE PRICE | E9: TOTAL CASH OUTLAY | H9: MONTHLY MORTGAGE PMT
B10: =Calculator!C7 -> 75000 | E10: =Calculator!F13 -> 36750 | H10: =Calculator!F12 -> 325.76267
B12: ANNUAL CASH FLOW (Outsourced PM) | E12: CASH ROI (Outsourced PM) | H12: NET OPERATING INCOME (Yr 1)
B13: =Calculator!E34 -> 5375.248 | E13: =Calculator!E37 -> 0.14626525 | H13: =Calculator!E32 -> 9284.4
B15: ANNUAL CASH FLOW (Self-Managed) | E15: CASH ROI (Self-Managed) | H15: TOTAL ROI (Year 1)
B16: =Calculator!H34 -> 6560.848 | E16: =Calculator!H37 -> 0.17852648 | H16: =Calculator!E38 -> 0.16621192
A19: 📋 YEAR 1 RESULTS OVERVIEW
B20: METRIC | E20: OUTSOURCED PM | H20: SELF-MANAGED
B21: Gross Annual Rent | E21: =Calculator!E19 -> 15600 | H21: =Calculator!H19 -> 15600
B22: Vacancy / Credit Loss | E22: =Calculator!E20 -> -780 | H22: =Calculator!H20 -> -780
B23: Effective Gross Income | E23: =Calculator!E21 -> 14820 | H23: =Calculator!H21 -> 14820
B24: Total Operating Expenses | E24: =Calculator!E30 -> -5535.6 | H24: =Calculator!H30 -> -4350
B25: Net Operating Income (NOI) | E25: =Calculator!E32 -> 9284.4 | H25: =Calculator!H32 -> 10470
B26: Annual Mortgage | E26: =Calculator!E33 -> -3909.152 | H26: =Calculator!H33 -> -3909.152
B27: Annual Cash Flow | E27: =Calculator!E34 -> 5375.248 | H27: =Calculator!H34 -> 6560.848
B28: Monthly Cash Flow | E28: =Calculator!E35 -> 447.93733 | H28: =Calculator!H35 -> 546.73733
B29: Cash ROI | E29: =Calculator!E37 -> 0.14626525 | H29: =Calculator!H37 -> 0.17852648
B30: Total ROI (CF + Equity, Yr1) | E30: =Calculator!E38 -> 0.16621192 | H30: =Calculator!H38 -> 0.19847315
B31: Cap Rate | E31: =Calculator!E39 -> 0.099832258 | H31: =Calculator!H39 -> 0.11258065
B32: Gross Rent Multiplier (GRM) | E32: =Calculator!E40 -> 4.8076923 | H32: =Calculator!H40 -> 4.8076923
A34: © 2025 DealWiseRent.com | Professional Rental Investment Analysis | www.DealWiseRent.com

Sheet Charts
A1: DealWiseRent.com | Investment Performance Charts
A2: 📈 Visual analysis of your 30-year rental property investment performance
A89: ⚠ DISCLAIMER: All charts are estimates for informational purposes only. DealWiseRent.com assumes no liability for investment decisions. © 2025 DealWiseRent.com – www.DealWiseRent.com
A90: © 2025 DealWiseRent.com | www.DealWiseRent.com
